Workbook
Name aporte: Simulador!$D$13
Name patrimonio: Simulador!$D$17
Name qtd_anos: Simulador!$D$14
Name rendimento_carteira: Simulador!$D$40
Name salario: Simulador!$D$39
Name sugestao_investimento: Simulador!$D$41
Name taxa_mensal: Simulador!$D$15

Sheet Simulador
B12: INDICADORES FINANCEIROS
B13: Aporte mensal | D13: 800
B14: Prazo do investimento (anos) | D14: 8
B15: Rentabilidade mensal | D15: 0.01079
B16: Dividend Yield Anual | D16: =taxa_mensal*12 -> 0.12948
B17: Patrimônio Acumulado | D17: =FV(taxa_mensal,qtd_anos*12,aporte*-1) -> 133596.48
B18: Total Investido | D18: =aporte*(qtd_anos*12) -> 76800
B19: Lucro Acumulado | D19: =patrimonio-D18 -> 56796.48
B20: Dividendos Mensais | D20: =patrimonio*rendimento_carteira -> 1335.9648
B21: Renda Passiva Anual | D21: =D20*12 -> 16031.578
B24: Simulador de Meta Financeira
B25: Meta de Renda Passiva | D25: 5000
B26: Rentabilidade média da carteira | D26: 0.008
B27: Patrimônio Necessário | D27: =D25/D26 -> 625000
B30: Cenários de Crescimento | D30: Dividendo
A31: 2 | B31: 2 Anos | C31: =FV($D$15,2*12,aporte*-1) -> 21782.102 | D31: =C31*rendimento_carteira -> 217.82102
A32: 5 | B32: 5 Anos | C32: =FV($D$15,$A32*12,$D$13*-1) -> 67021.531 | D32: =C32*rendimento_carteira -> 670.21531
A33: 10 | B33: 10 Anos | C33: =FV($D$15,$A33*12,$D$13*-1) -> 194627.37 | D33: =C33*rendimento_carteira -> 1946.2737
A34: 20 | B34: 20 Anos | C34: =FV($D$15,$A34*12,$D$13*-1) -> 900158.72 | D34: =C34*rendimento_carteira -> 9001.5872
A35: 30 | B35: 30 Anos | C35: =FV($D$15,$A35*12,$D$13*-1) -> 3457735.7 | D35: =C35*rendimento_carteira -> 34577.357
B38: Configurações da Simulação
B39: Salário | D39: 4500
B40: Rendimento Carteira | D40: 0.01
B41: Sugestão de Investimento (30%) | D41: =D39*30% -> 1350
B45: Perfil do Investidor | C45: Agressivo
B46: VALOR A SER INVESTIDO POR MÊS | C46: =aporte -> 800
B48: TIPO DE FII | C48: (%) Sugerido | D48: Valores
B49: PAPEL | C49: =VLOOKUP($C$45&"-"&B49,'Tipo de Fundos'!$A:$D,4,FALSE) -> 0.5 | D49: =C49*$C$46 -> 400
B50: TIJOLO | C50: =VLOOKUP($C$45&"-"&B50,'Tipo de Fundos'!$A:$D,4,FALSE) -> 0.1 | D50: =C50*$C$46 -> 80
B51: HÍBRIDOS | C51: =VLOOKUP($C$45&"-"&B51,'Tipo de Fundos'!$A:$D,4,FALSE) -> 0.05 | D51: =C51*$C$46 -> 40
B52: FOFs | C52: =VLOOKUP($C$45&"-"&B52,'Tipo de Fundos'!$A:$D,4,FALSE) -> 0.05 | D52: =C52*$C$46 -> 40
B53: DESENVOLVIMENTO | C53: =VLOOKUP($C$45&"-"&B53,'Tipo de Fundos'!$A:$D,4,FALSE) -> 0.2 | D53: =C53*$C$46 -> 160
B54: HOTELARIAS | C54: =VLOOKUP($C$45&"-"&B54,'Tipo de Fundos'!$A:$D,4,FALSE) -> 0.1 | D54: =C54*$C$46 -> 80
D55: =SUM(D49:D54) -> 800

Sheet Tipo de Fundos
A2: CHAVE | B2: PERFIL | C2: TIPO DE FII | D2: %
A3: =B3&"-"&C3 -> Conservador-PAPEL | B3: Conservador | C3: PAPEL | D3: 0.3
A4: =B4&"-"&C4 -> Conservador-TIJOLO | B4: Conservador | C4: TIJOLO | D4: 0.5
A5: =B5&"-"&C5 -> Conservador-HÍBRIDOS | B5: Conservador | C5: HÍBRIDOS | D5: 0.1
A6: =B6&"-"&C6 -> Conservador-FOFs | B6: Conservador | C6: FOFs | D6: 0.1
A7: =B7&"-"&C7 -> Conservador-DESENVOLVIMENTO | B7: Conservador | C7: DESENVOLVIMENTO | D7: 0
A8: =B8&"-"&C8 -> Conservador-HOTELARIAS | B8: Conservador | C8: HOTELARIAS | D8: 0
A9: =B9&"-"&C9 -> Moderado-PAPEL | B9: Moderado | C9: PAPEL | D9: 0.32
A10: =B10&"-"&C10 -> Moderado-TIJOLO | B10: Moderado | C10: TIJOLO | D10: 0.35
A11: =B11&"-"&C11 -> Moderado-HÍBRIDOS | B11: Moderado | C11: HÍBRIDOS | D11: 0.08
A12: =B12&"-"&C12 -> Moderado-FOFs | B12: Moderado | C12: FOFs | D12: 0.05
A13: =B13&"-"&C13 -> Moderado-DESENVOLVIMENTO | B13: Moderado | C13: DESENVOLVIMENTO | D13: 0.1
A14: =B14&"-"&C14 -> Moderado-HOTELARIAS | B14: Moderado | C14: HOTELARIAS | D14: 0.1
... A20: =B20&"-"&C20 -> Agressivo-HOTELARIAS | B20: Agressivo | C20: HOTELARIAS | D20: 0.1
